napari_ufish/__init__.py
napari_ufish/_sample_data.py
napari_ufish/_widget.py
napari_ufish/napari.yaml
napari_ufish/_tests/__init__.py
napari_ufish/_tests/test_sample_data.py
napari_ufish/_tests/test_widget.py
napari_ufish/sample_data/sample1.tif
napari_ufish-0.0.1.dist-info/LICENSE
napari_ufish-0.0.1.dist-info/METADATA
napari_ufish-0.0.1.dist-info/WHEEL
napari_ufish-0.0.1.dist-info/entry_points.txt
napari_ufish-0.0.1.dist-info/top_level.txt
napari_ufish-0.0.1.dist-info/RECORD
